hybridlane/__init__.py
hybridlane/decomposition/__init__.py
hybridlane/decomposition/graph_decomposition.py
hybridlane/decomposition/resources.py
hybridlane/decomposition/symbolic_decomposition.py
hybridlane/decomposition/utils.py
hybridlane/devices/__init__.py
hybridlane/devices/bosonic_qiskit/__init__.py
hybridlane/devices/bosonic_qiskit/device.py
hybridlane/devices/bosonic_qiskit/gates.py
hybridlane/devices/bosonic_qiskit/register_mapping.py
hybridlane/devices/bosonic_qiskit/simulate.py
hybridlane/devices/preprocess.py
hybridlane/devices/sandia_qscout/__init__.py
hybridlane/devices/sandia_qscout/device.py
hybridlane/devices/sandia_qscout/draw.py
hybridlane/devices/sandia_qscout/jaqal.py
hybridlane/devices/sandia_qscout/ops.py
hybridlane/drawer/__init__.py
hybridlane/drawer/draw.py
hybridlane/drawer/mpldrawer.py
hybridlane/drawer/tape_mpl.py
hybridlane/io/__init__.py
hybridlane/io/openqasm.py
hybridlane/measurements/__init__.py
hybridlane/measurements/base.py
hybridlane/measurements/counts.py
hybridlane/measurements/expectation.py
hybridlane/measurements/probability.py
hybridlane/measurements/sample.py
hybridlane/measurements/variance.py
hybridlane/ops/__init__.py
hybridlane/ops/attributes.py
hybridlane/ops/hybrid/__init__.py
hybridlane/ops/hybrid/non_parametric_ops.py
hybridlane/ops/hybrid/parametric_ops_multi_qumode.py
hybridlane/ops/hybrid/parametric_ops_single_qumode.py
hybridlane/ops/mixins.py
hybridlane/ops/op_math/__init__.py
hybridlane/ops/op_math/decompositions/__init__.py
hybridlane/ops/op_math/decompositions/qubit_conditioned_decompositions.py
hybridlane/ops/op_math/qubit_conditioned.py
hybridlane/ops/qumode/__init__.py
hybridlane/ops/qumode/non_parametric_ops.py
hybridlane/ops/qumode/observables.py
hybridlane/ops/qumode/parametric_ops_multi_qumode.py
hybridlane/ops/qumode/parametric_ops_single_qumode.py
hybridlane/sa/__init__.py
hybridlane/sa/base.py
hybridlane/sa/exceptions.py
hybridlane/sa/infer_wires.py
hybridlane/templates/__init__.py
hybridlane-0.5.1a1.dist-info/licenses/DISCLAIMER.txt
hybridlane-0.5.1a1.dist-info/licenses/LICENSE.txt
hybridlane-0.5.1a1.dist-info/WHEEL
hybridlane-0.5.1a1.dist-info/entry_points.txt
hybridlane-0.5.1a1.dist-info/METADATA
hybridlane-0.5.1a1.dist-info/RECORD
