Metadata-Version: 2.4
Name: hybridlane
Version: 0.5.1a1
Summary: A frontend library for hybrid CV-DV computation based on Pennylane.
Author: Jim Furches
Author-email: Jim Furches <james.furches@pnnl.gov>
License-Expression: BSD-2-Clause
License-File: DISCLAIMER.txt
License-File: LICENSE.txt
Classifier: Development Status :: 3 - Alpha
Classifier: Programming Language :: Python :: 3
Classifier: Programming Language :: Python :: 3.11
Classifier: Programming Language :: Python :: 3.12
Classifier: Programming Language :: Python :: 3.13
Requires-Dist: pennylane>=0.43.0
Requires-Dist: pydantic>=2.9.2
Requires-Dist: hybridlane[bq,qscout] ; extra == 'all'
Requires-Dist: bosonic-qiskit>=15.0 ; extra == 'bq'
Requires-Dist: sparse>=0.17.0 ; extra == 'bq'
Requires-Dist: python-constraint2>=2.4.0 ; extra == 'qscout'
Requires-Python: >=3.11
Project-URL: Documentation, https://pnnl.github.io/hybridlane/
Project-URL: Homepage, https://github.com/pnnl/hybridlane
Project-URL: Issues, https://github.com/pnnl/hybridlane/issues
Project-URL: Repository, https://github.com/pnnl/hybridlane.git
Provides-Extra: all
Provides-Extra: bq
Provides-Extra: qscout
